latex_generator/__init__.py
latex_generator/latex_generator.py
latex_generator_VILGIZ/__init__.py
latex_generator_VILGIZ/latex_generator.py
latex_generator_VILGIZ-0.1.6.dist-info/METADATA
latex_generator_VILGIZ-0.1.6.dist-info/WHEEL
latex_generator_VILGIZ-0.1.6.dist-info/top_level.txt
latex_generator_VILGIZ-0.1.6.dist-info/RECORD
