Metadata-Version: 2.1
Name: latex-generator-VILGIZ
Version: 0.1.6
Summary: LaTeX table and image generator
Author: VILGIZ
